apim/__init__.py
apim/__main__.py
auto_play_in_mpv-0.1.2.dist-info/METADATA
auto_play_in_mpv-0.1.2.dist-info/WHEEL
auto_play_in_mpv-0.1.2.dist-info/entry_points.txt
auto_play_in_mpv-0.1.2.dist-info/licenses/LICENSE
auto_play_in_mpv-0.1.2.dist-info/RECORD
