Metadata-Version: 2.3
Name: auto-play-in-mpv
Version: 0.1.2
Summary: Automatically redirect to mpv player when playing online video
Project-URL: Homepage, https://github.com/lxl66566/auto-play-in-mpv
Project-URL: Repository, https://github.com/lxl66566/auto-play-in-mpv.git
License-File: LICENSE
Keywords: mpv,video
Classifier: License :: OSI Approved :: MIT License
Classifier: Programming Language :: Python :: 3
Classifier: Programming Language :: Python :: 3.8
Classifier: Programming Language :: Python :: 3.9
Classifier: Programming Language :: Python :: 3.10
Classifier: Programming Language :: Python :: 3.11
Classifier: Programming Language :: Python :: 3.12
Requires-Python: >=3.8
Requires-Dist: validators
Requires-Dist: websockets>=13.0
